client/__init__.py
client/config.py
client/connection.py
client/main.py
client/ui.py
shared/__init__.py
shared/crypto.py
terminal_chat_client-1.0.0.dist-info/METADATA
terminal_chat_client-1.0.0.dist-info/WHEEL
terminal_chat_client-1.0.0.dist-info/entry_points.txt
terminal_chat_client-1.0.0.dist-info/top_level.txt
terminal_chat_client-1.0.0.dist-info/RECORD
