Metadata-Version: 2.4
Name: terminal-chat-client
Version: 1.0.0
Summary: A secure end-to-end encrypted terminal-based chat client
Author-email: Fuad Muhammed <fuad@example.com>
License: MIT
Project-URL: Homepage, https://terminal-chat.fuadmuhammed.com
Project-URL: Source, https://github.com/yourusername/terminal-chat
Project-URL: Bug Reports, https://github.com/yourusername/terminal-chat/issues
Keywords: chat,terminal,encryption,e2e,websocket,textual
Classifier: Development Status :: 4 - Beta
Classifier: Intended Audience :: End Users/Desktop
Classifier: Topic :: Communications :: Chat
Classifier: License :: OSI Approved :: MIT License
Classifier: Programming Language :: Python :: 3
Classifier: Programming Language :: Python :: 3.8
Classifier: Programming Language :: Python :: 3.9
Classifier: Programming Language :: Python :: 3.10
Classifier: Programming Language :: Python :: 3.11
Classifier: Programming Language :: Python :: 3.12
Classifier: Operating System :: OS Independent
Classifier: Environment :: Console
Requires-Python: >=3.8
Requires-Dist: textual>=0.44.1
Requires-Dist: aiohttp>=3.9.1
Requires-Dist: websockets>=12.0
Requires-Dist: cryptography>=43.0.0
Provides-Extra: dev
Requires-Dist: build>=1.0.0; extra == "dev"
Requires-Dist: twine>=4.0.0; extra == "dev"
